MANIFEST.in
README.rst
setup.py
makesite/__init__.py
makesite/__init__.pyc
makesite/core.py
makesite/core.pyc
makesite/install.py
makesite/install.pyc
makesite/main.py
makesite/main.pyc
makesite/makesite.ini
makesite/remote.py
makesite/remote.pyc
makesite/settings.py
makesite/settings.pyc
makesite/shell.sh
makesite/site.py
makesite/site.pyc
makesite/terminal.py
makesite/terminal.pyc
makesite.egg-info/PKG-INFO
makesite.egg-info/SOURCES.txt
makesite.egg-info/dependency_links.txt
makesite.egg-info/entry_points.txt
makesite.egg-info/requires.txt
makesite.egg-info/top_level.txt
makesite/modules/django/Makefile
makesite/modules/django/__init__.py
makesite/modules/django/initial_data.json
makesite/modules/django/makesite.ini
makesite/modules/django/manage.py
makesite/modules/django/requirements.txt
makesite/modules/django/wsgi.py
makesite/modules/django/main/__init__.py
makesite/modules/django/main/admin.py
makesite/modules/django/main/models.py
makesite/modules/django/main/urls.py
makesite/modules/django/main/views.py
makesite/modules/django/main/static/main.css
makesite/modules/django/main/static/main.js
makesite/modules/django/main/static/print.css
makesite/modules/django/main/templates/404.html
makesite/modules/django/main/templates/500.html
makesite/modules/django/main/templates/base.html
makesite/modules/django/main/templates/main/head.html
makesite/modules/django/main/templates/main/index.html
makesite/modules/django/main/templates/main/layout.html
makesite/modules/django/main/tests/__init__.py
makesite/modules/django/main/tests/base.py
makesite/modules/django/main/utils/__init__.py
makesite/modules/django/main/utils/cache.py
makesite/modules/django/main/utils/files.py
makesite/modules/django/main/utils/models.py
makesite/modules/django/main/utils/views.py
makesite/modules/django/settings/__init__.py
makesite/modules/django/settings/core.py
makesite/modules/django/settings/dev.py
makesite/modules/django/settings/project.py
makesite/modules/django/settings/test.py
makesite/modules/flask/Changelog
makesite/modules/flask/Makefile
makesite/modules/flask/README.rst
makesite/modules/flask/makesite.ini
makesite/modules/flask/manage.py
