Metadata-Version: 1.1
Name: makesite
Version: 0.9.83
Summary: Makesite is collection scripts for make and control site structure.
